delogger/__init__.py
delogger/decorators/__init__.py
delogger/decorators/base.py
delogger/decorators/debug_log.py
delogger/decorators/line_memory_profile.py
delogger/decorators/line_profile.py
delogger/decorators/memory_profile.py
delogger/decorators/profiles.py
delogger/filters/__init__.py
delogger/filters/only_filter.py
delogger/handlers/__init__.py
delogger/handlers/count_rotating_file.py
delogger/handlers/delogger_queue.py
delogger/handlers/slack.py
delogger/loggers/__init__.py
delogger/loggers/base.py
delogger/loggers/delogger.py
delogger/loggers/delogger_queue.py
delogger/modes/__init__.py
delogger/modes/base.py
delogger/modes/file.py
delogger/modes/propagate.py
delogger/modes/slack.py
delogger/modes/stream.py
delogger/presets/__init__.py
delogger/presets/base.py
delogger/presets/debug.py
delogger/presets/debug_stream.py
delogger/presets/info.py
delogger/presets/output.py
delogger/presets/profiler.py
delogger/util/__init__.py
delogger/util/log_file.py
delogger/util/warn.py
delogger-0.3.0.dist-info/LICENSE
delogger-0.3.0.dist-info/WHEEL
delogger-0.3.0.dist-info/METADATA
delogger-0.3.0.dist-info/RECORD
