Metadata-Version: 2.1
Name: delogger
Version: 0.3.0
Summary: delogger is a convenient logging package
Home-page: https://github.com/deresmos/delogger
License: MIT
Keywords: logging,Logger
Author: deresmos
Author-email: deresmos@gmail.com
Requires-Python: >=3.6,<4.0
Classifier: License :: OSI Approved :: MIT License
Classifier: Programming Language :: Python :: 3
Classifier: Programming Language :: Python :: 3.6
Classifier: Programming Language :: Python :: 3.7
Classifier: Programming Language :: Python :: 3.8
Classifier: Programming Language :: Python :: 3.9
Requires-Dist: colorlog (>=4.2.1,<5.0.0)
Project-URL: Repository, https://github.com/deresmos/delogger
